{
  "margins": [
    "< 5%",
    "5-10%",
    "10-20%",
    "> 20%"
  ],
  "polymarket": {
    "brier": [
      0.0468,
      NaN,
      NaN,
      NaN
    ],
    "count": [
      1049,
      0,
      0,
      0
    ]
  },
  "kalshi": {
    "brier": [
      0.0701,
      NaN,
      NaN,
      NaN
    ],
    "count": [
      520,
      0,
      0,
      0
    ]
  },
  "combined": {
    "brier": [
      0.0545,
      NaN,
      NaN,
      NaN
    ],
    "count": [
      1569,
      0,
      0,
      0
    ]
  }
}