{
  "all_elections": {
    "polymarket": {
      "n": 100,
      "brier": 0.0819,
      "accuracy": 0.87
    },
    "kalshi": {
      "n": 102,
      "brier": 0.1013,
      "accuracy": 0.8824
    }
  },
  "shared_elections": {
    "polymarket": {
      "n": 71,
      "brier": 0.1091,
      "accuracy": 0.8169
    },
    "kalshi": {
      "n": 71,
      "brier": 0.1108,
      "accuracy": 0.8732
    },
    "combined": {
      "n": 69,
      "brier": 0.1101,
      "accuracy": 0.8551
    }
  },
  "head_to_head": {
    "n_shared": 71,
    "correlation": 0.8855,
    "pm_wins": 41,
    "kalshi_wins": 30,
    "ties": 0,
    "p_value": 0.8622
  }
}